nostr_tools/__init__.py
nostr_tools/_version.py
nostr_tools/py.typed
nostr_tools/actions/__init__.py
nostr_tools/actions/actions.py
nostr_tools/core/__init__.py
nostr_tools/core/client.py
nostr_tools/core/event.py
nostr_tools/core/filter.py
nostr_tools/core/relay.py
nostr_tools/core/relay_metadata.py
nostr_tools/exceptions/__init__.py
nostr_tools/exceptions/errors.py
nostr_tools/utils/__init__.py
nostr_tools/utils/utils.py
nostr_tools-1.4.0.dist-info/LICENSE
nostr_tools-1.4.0.dist-info/METADATA
nostr_tools-1.4.0.dist-info/WHEEL
nostr_tools-1.4.0.dist-info/top_level.txt
nostr_tools-1.4.0.dist-info/RECORD
