Metadata-Version: 2.1
Name: nostr-tools
Version: 1.4.0
Summary: A comprehensive Python library for Nostr protocol interactions
Author-email: Bigbrotr <hello@bigbrotr.com>
Maintainer-email: Bigbrotr <hello@bigbrotr.com>
License: MIT
Project-URL: Homepage, https://github.com/bigbrotr/nostr-tools
Project-URL: Documentation, https://bigbrotr.github.io/nostr-tools/
Project-URL: Repository, https://github.com/bigbrotr/nostr-tools.git
Project-URL: Bug Reports, https://github.com/bigbrotr/nostr-tools/issues
Project-URL: Source Code, https://github.com/bigbrotr/nostr-tools
Project-URL: Changelog, https://github.com/bigbrotr/nostr-tools/blob/main/CHANGELOG.md
Project-URL: Funding, https://github.com/sponsors/bigbrotr
Keywords: nostr,decentralized,social,protocol,websocket,cryptography,bitcoin,schnorr,secp256k1,relay,lightning-network
Classifier: Development Status :: 4 - Beta
Classifier: Intended Audience :: Developers
Classifier: License :: OSI Approved :: MIT License
Classifier: Operating System :: OS Independent
Classifier: Programming Language :: Python :: 3
Classifier: Programming Language :: Python :: 3.9
Classifier: Programming Language :: Python :: 3.10
Classifier: Programming Language :: Python :: 3.11
Classifier: Programming Language :: Python :: 3.12
Classifier: Programming Language :: Python :: 3.13
Classifier: Topic :: Software Development :: Libraries :: Python Modules
Classifier: Topic :: Internet :: WWW/HTTP
Classifier: Topic :: Communications
Classifier: Topic :: Security :: Cryptography
Classifier: Framework :: AsyncIO
Classifier: Typing :: Typed
Requires-Python: >=3.9
License-File: LICENSE
Requires-Dist: secp256k1<1.0.0,>=0.14.0
Requires-Dist: bech32<2.0.0,>=1.2.0
Requires-Dist: aiohttp<4.0.0,>=3.8.0
Requires-Dist: aiohttp-socks<1.0.0,>=0.8.0
Requires-Dist: typing-extensions>=4.0.0; python_version < "3.9"
Provides-Extra: all
Requires-Dist: nostr-tools[dev,docs,security,test]; extra == "all"
Provides-Extra: dev
Requires-Dist: pytest<8.0.0,>=7.4.0; extra == "dev"
Requires-Dist: pytest-asyncio<0.24.0,>=0.23.0; extra == "dev"
Requires-Dist: pytest-cov<5.0.0,>=4.0.0; extra == "dev"
Requires-Dist: pytest-mock<4.0.0,>=3.12.0; extra == "dev"
Requires-Dist: pytest-timeout<3.0.0,>=2.1.0; extra == "dev"
Requires-Dist: pytest-xdist<4.0.0,>=3.3.0; extra == "dev"
Requires-Dist: ruff<1.0.0,>=0.4.0; extra == "dev"
Requires-Dist: mypy<2.0.0,>=1.8.0; extra == "dev"
Requires-Dist: pre-commit<4.0.0,>=3.5.0; extra == "dev"
Requires-Dist: build<2.0.0,>=0.10.0; extra == "dev"
Requires-Dist: twine<6.0.0,>=4.0.0; extra == "dev"
Requires-Dist: setuptools-scm<9.0.0,>=7.0.0; extra == "dev"
Requires-Dist: bandit[toml]<2.0.0,>=1.7.0; extra == "dev"
Requires-Dist: safety<4.0.0,>=2.3.0; extra == "dev"
Requires-Dist: pip-audit<3.0.0,>=2.6.0; extra == "dev"
Requires-Dist: sphinx<8.0.0,>=7.2.0; extra == "dev"
Requires-Dist: sphinx-rtd-theme<4.0.0,>=1.3.0; extra == "dev"
Requires-Dist: myst-parser<4.0.0,>=0.19.0; extra == "dev"
Requires-Dist: sphinx-autodoc-typehints<3.0.0,>=1.24.0; extra == "dev"
Requires-Dist: sphinxext-opengraph<1.0.0,>=0.8.0; extra == "dev"
Requires-Dist: sphinx-design<1.0.0,>=0.4.0; extra == "dev"
Requires-Dist: furo>=2025.7.19; extra == "dev"
Provides-Extra: docs
Requires-Dist: sphinx<8.0.0,>=7.2.0; extra == "docs"
Requires-Dist: sphinx-rtd-theme<4.0.0,>=1.3.0; extra == "docs"
Requires-Dist: myst-parser<4.0.0,>=0.19.0; extra == "docs"
Requires-Dist: sphinx-autodoc-typehints<3.0.0,>=1.24.0; extra == "docs"
Requires-Dist: sphinxext-opengraph<1.0.0,>=0.8.0; extra == "docs"
Requires-Dist: sphinx-design<1.0.0,>=0.4.0; extra == "docs"
Requires-Dist: furo>=2025.7.19; extra == "docs"
Provides-Extra: security
Requires-Dist: bandit[toml]<2.0.0,>=1.7.0; extra == "security"
Requires-Dist: safety<4.0.0,>=2.3.0; extra == "security"
Requires-Dist: pip-audit<3.0.0,>=2.6.0; extra == "security"
Provides-Extra: test
Requires-Dist: pytest<8.0.0,>=7.4.0; extra == "test"
Requires-Dist: pytest-asyncio<0.24.0,>=0.23.0; extra == "test"
Requires-Dist: pytest-cov<5.0.0,>=4.0.0; extra == "test"
Requires-Dist: pytest-mock<4.0.0,>=3.12.0; extra == "test"
Requires-Dist: pytest-timeout<3.0.0,>=2.1.0; extra == "test"
Requires-Dist: pytest-xdist<4.0.0,>=3.3.0; extra == "test"
